multitaskflow/__init__.py
multitaskflow/process_monitor.py
multitaskflow/task_flow.py
multitaskflow/web/__init__.py
multitaskflow/web/history.py
multitaskflow/web/manager.py
multitaskflow/web/notify.py
multitaskflow/web/queue_manager.py
multitaskflow/web/server.py
multitaskflow/web/state.py
multitaskflow/web/watcher.py
multitaskflow/web/ws.py
multitaskflow/web/api/__init__.py
multitaskflow/web/api/auth.py
multitaskflow/web/api/execute.py
multitaskflow/web/api/notification.py
multitaskflow/web/api/queues.py
multitaskflow/web/api/tasks.py
multitaskflow/web/static/app.js
multitaskflow/web/static/index.html
multitaskflow/web/static/style.css
multitaskflow/web/static/dist/index.html
multitaskflow/web/static/dist/vite.svg
multitaskflow/web/static/dist/assets/index-BkmCBLXC.js
multitaskflow/web/static/dist/assets/index-ebJcCEl3.css
multitaskflow-1.0.0.dist-info/licenses/LICENSE
multitaskflow-1.0.0.dist-info/METADATA
multitaskflow-1.0.0.dist-info/WHEEL
multitaskflow-1.0.0.dist-info/entry_points.txt
multitaskflow-1.0.0.dist-info/top_level.txt
multitaskflow-1.0.0.dist-info/RECORD
