Metadata-Version: 2.4
Name: multitaskflow
Version: 1.0.0
Summary: 一个用于管理和监控多个任务执行的Python工具，支持CLI和Web UI
Author-email: Polaris <polaris0532@outlook.com>
License-Expression: MIT
Project-URL: Homepage, https://github.com/Polaris-F/MultiTaskFlow
Project-URL: Bug Tracker, https://github.com/Polaris-F/MultiTaskFlow/issues
Project-URL: 主页, https://github.com/Polaris-F/MultiTaskFlow
Project-URL: 问题追踪, https://github.com/Polaris-F/MultiTaskFlow/issues
Classifier: Development Status :: 5 - Production/Stable
Classifier: Intended Audience :: Developers
Classifier: Intended Audience :: Science/Research
Classifier: Programming Language :: Python :: 3
Classifier: Programming Language :: Python :: 3.7
Classifier: Programming Language :: Python :: 3.8
Classifier: Programming Language :: Python :: 3.9
Classifier: Programming Language :: Python :: 3.10
Classifier: Operating System :: OS Independent
Classifier: Topic :: Scientific/Engineering
Classifier: Topic :: Software Development :: Libraries
Requires-Python: >=3.6
License-File: LICENSE
Requires-Dist: pyyaml>=5.1
Requires-Dist: psutil>=5.8.0
Requires-Dist: python-dotenv>=0.19.0
Requires-Dist: requests>=2.25.0
Provides-Extra: color
Requires-Dist: colorama>=0.4.0; extra == "color"
Provides-Extra: web
Requires-Dist: fastapi>=0.100.0; extra == "web"
Requires-Dist: uvicorn[standard]>=0.23.0; extra == "web"
Requires-Dist: watchdog>=3.0.0; extra == "web"
Dynamic: license-file
